Workbook

Sheet RESUMEN Y BALANCE
A1: CONCURSO COLOMBIANO DE COHETERÍA DEPORTIVA 2026 (CCCD 2026)
A2: Delegación PDA (Noctux, Stars, Rocketeers) — Institución Educativa José Antonio Galán
A3: TABLERO DE CONTROL FINANCIERO: PRESUPUESTO PROYECTADO VS. GASTOS REALES EJECUTADOS
A5: RUBRO FINANCIERO | B5: PRESUPUESTO ESTIMADO (COP) | C5: GASTO REAL EJECUTADO (COP) | D5: SALDO DISPONIBLE (COP) | E5: % EJECUCIÓN | F5: ESTADO
A6: Propulsión y Motores Certificados | B6: =SUMIF(PRESUPUESTO!B:B, A6, PRESUPUESTO!H:H) -> 0 | C6: =SUMIF(RELACION_GASTOS!E:E, A6, RELACION_GASTOS!H:H) -> 0 | D6: =B6-C6 -> 0 | E6: =IF(B6>0, C6/B6, 0) -> 0 | F6: =IF(C6>B6, "SOBREGIRO", IF(C6=B6, "EJECUTADO 100%", IF(C6>0, "EN EJECUCIÓN", "SIN INICIAR"))) -> EJECUTADO 100%
A7: Estructura Aerodinámica y Fuselaje | B7: =SUMIF(PRESUPUESTO!B:B, A7, PRESUPUESTO!H:H) -> 1025000 | C7: =SUMIF(RELACION_GASTOS!E:E, A7, RELACION_GASTOS!H:H) -> 0 | D7: =B7-C7 -> 1025000 | E7: =IF(B7>0, C7/B7, 0) -> 0 | F7: =IF(C7>B7, "SOBREGIRO", IF(C7=B7, "EJECUTADO 100%", IF(C7>0, "EN EJECUCIÓN", "SIN INICIAR"))) -> SIN INICIAR
A8: Sistema de Recuperación y Seguridad | B8: =SUMIF(PRESUPUESTO!B:B, A8, PRESUPUESTO!H:H) -> 205000 | C8: =SUMIF(RELACION_GASTOS!E:E, A8, RELACION_GASTOS!H:H) -> 0 | D8: =B8-C8 -> 205000 | E8: =IF(B8>0, C8/B8, 0) -> 0 | F8: =IF(C8>B8, "SOBREGIRO", IF(C8=B8, "EJECUTADO 100%", IF(C8>0, "EN EJECUCIÓN", "SIN INICIAR"))) -> SIN INICIAR
A9: Aviónica, Telemetría y Carga Útil | B9: =SUMIF(PRESUPUESTO!B:B, A9, PRESUPUESTO!H:H) -> 1300000 | C9: =SUMIF(RELACION_GASTOS!E:E, A9, RELACION_GASTOS!H:H) -> 0 | D9: =B9-C9 -> 1300000 | E9: =IF(B9>0, C9/B9, 0) -> 0 | F9: =IF(C9>B9, "SOBREGIRO", IF(C9=B9, "EJECUTADO 100%", IF(C9>0, "EN EJECUCIÓN", "SIN INICIAR"))) -> SIN INICIAR
A10: Herramientas de Taller y Consumibles | B10: =SUMIF(PRESUPUESTO!B:B, A10, PRESUPUESTO!H:H) -> 660000 | C10: =SUMIF(RELACION_GASTOS!E:E, A10, RELACION_GASTOS!H:H) -> 0 | D10: =B10-C10 -> 660000 | E10: =IF(B10>0, C10/B10, 0) -> 0 | F10: =IF(C10>B10, "SOBREGIRO", IF(C10=B10, "EJECUTADO 100%", IF(C10>0, "EN EJECUCIÓN", "SIN INICIAR"))) -> SIN INICIAR
A11: Logística de Lanzamiento, Transporte y Campo | B11: =SUMIF(PRESUPUESTO!B:B, A11, PRESUPUESTO!H:H) -> 3900000 | C11: =SUMIF(RELACION_GASTOS!E:E, A11, RELACION_GASTOS!H:H) -> 0 | D11: =B11-C11 -> 3900000 | E11: =IF(B11>0, C11/B11, 0) -> 0 | F11: =IF(C11>B11, "SOBREGIRO", IF(C11=B11, "EJECUTADO 100%", IF(C11>0, "EN EJECUCIÓN", "SIN INICIAR"))) -> SIN INICIAR
A12: Inscripciones, Pólizas y Administrativo | B12: =SUMIF(PRESUPUESTO!B:B, A12, PRESUPUESTO!H:H) -> 900000 | C12: =SUMIF(RELACION_GASTOS!E:E, A12, RELACION_GASTOS!H:H) -> 0 | D12: =B12-C12 -> 900000 | E12: =IF(B12>0, C12/B12, 0) -> 0 | F12: =IF(C12>B12, "SOBREGIRO", IF(C12=B12, "EJECUTADO 100%", IF(C12>0, "EN EJECUCIÓN", "SIN INICIAR"))) -> SIN INICIAR
A13: TOTAL CONSOLIDADO | B13: =SUM(B6:B12) -> 7990000 | C13: =SUM(C6:C12) -> 0 | D13: =SUM(D6:D12) -> 7990000 | E13: =IF(B13>0, C13/B13, 0) -> 0 | F13: =IF(C13>B13, "ALERTA SOBREGIRO", "PRESUPUESTO DISPONIBLE") -> PRESUPUESTO DISPONIBLE

Sheet PRESUPUESTO
A1: PRESUPUESTO DETALLADO POR CATEGORÍA — CCCD 2026
A2: Propuesta Inicial General (3 Equipos PDA)
A4: ÍTEM | B4: RUBRO FINANCIERO | C4: ASIGNACIÓN (CAT/EQUIPO) | D4: DESCRIPCIÓN DEL ARTÍCULO / ESPECIFICACIÓN TÉCNICA | E4: CANTIDAD | F4: UNIDAD | G4: VALOR UNITARIO (COP) | H4: TOTAL PROYECTADO (COP) | I4: PRIORIDAD | J4: PROVEEDOR SUGERIDO | K4: OBSERVACIONES
A5: 1 | B5: Estructura Aerodinámica y Fuselaje | C5: Cat 1 - Noctux | D5: Tubo BT65 | E5: 1 | F5: Unidad | G5: 70000 | H5: =E5*G5 -> 70000 | I5: Media | J5: Proveedor local | K5: Cohete sencillo sin electrónica interna
A6: 2 | B6: Sistema de Recuperación y Seguridad | C6: Cat 1 - Noctux | D6: Cordón de choque | E6: 1 | F6: Unidad | G6: 10000 | H6: =E6*G6 -> 10000 | I6: Alta | J6: Confección propia
A7: 3 | B7: Estructura Aerodinámica y Fuselaje | C7: Cat 2 - Stars | D7: Tubo BT80 | E7: 1 | F7: Unidad | G7: 90000 | H7: =E7*G7 -> 90000 | I7: Alta | J7: Proveedor local
A8: 4 | B8: Aviónica, Telemetría y Carga Útil | C8: Cat 2 - Stars | D8: Altímetro Jolly Logic AltimeterOne | E8: 1 | F8: Unidad | G8: 250000 | H8: =E8*G8 -> 250000 | I8: Alta | J8: Jolly Logic / Amazon | K8: Altímetro obligatorio por reglamento
A9: 5 | B9: Aviónica, Telemetría y Carga Útil | C9: Cat 2 - Stars | D9: Electrónica | E9: 1 | F9: Lote | G9: 300000 | H9: =E9*G9 -> 300000 | I9: Media | J9: Tienda electrónica | K9: Valor por definir
A10: 6 | B10: Sistema de Recuperación y Seguridad | C10: Cat 2 - Stars | D10: Cordón de choque | E10: 1 | F10: Unidad | G10: 10000 | H10: =E10*G10 -> 10000 | I10: Alta | J10: Confección
A11: 7 | B11: Inscripciones, Pólizas y Administrativo | C11: Cat 2 - Stars | D11: Inscripción equipo PDA Stars al CCCD | E11: 1 | F11: Pago | G11: 900000 | H11: =E11*G11 -> 900000 | I11: Alta | J11: Organización CCCD | K11: Única inscripción pendiente por pagar
A12: 8 | B12: Estructura Aerodinámica y Fuselaje | C12: Cat 3 - Rocketeers | D12: Tubo cartón 4 pulgadas | E12: 2 | F12: Unidad | G12: 100000 | H12: =E12*G12 -> 200000 | I12: Alta | J12: Proveedores locales
A13: 9 | B13: Aviónica, Telemetría y Carga Útil | C13: Cat 3 - Rocketeers | D13: Altímetro Jolly Logic AltimeterOne | E13: 1 | F13: Unidad | G13: 250000 | H13: =E13*G13 -> 250000 | I13: Alta | J13: Jolly Logic / Amazon
A14: 10 | B14: Aviónica, Telemetría y Carga Útil | C14: Cat 3 - Rocketeers | D14: Electrónica | E14: 1 | F14: Lote | G14: 500000 | H14: =E14*G14 -> 500000 | I14: Media | J14: Tienda electrónica | K14: Valor por definir
A15: 11 | B15: Estructura Aerodinámica y Fuselaje | C15: Cat 3 - Rocketeers | D15: Tubo porta motor | E15: 1 | F15: Unidad | G15: 50000 | H15: =E15*G15 -> 50000 | I15: Alta | J15: Proveedores locales | K15: Valor por definir
A16: 12 | B16: Estructura Aerodinámica y Fuselaje | C16: Cat 3 - Rocketeers | D16: Madera para aletas | E16: 1 | F16: Lote | G16: 120000 | H16: =E16*G16 -> 120000 | I16: Alta | J16: Distribuidor local | K16: Valor por definir
A17: 13 | B17: Estructura Aerodinámica y Fuselaje | C17: Cat 3 - Rocketeers | D17: Molde para ojiva | E17: 1 | F17: Unidad | G17: 300000 | H17: =E17*G17 -> 300000 | I17: Alta | J17: Proveedores | K17: Valor por definir
A18: 14 | B18: Sistema de Recuperación y Seguridad | C18: Cat 3 - Rocketeers | D18: Cordón de choque | E18: 1 | F18: Unidad | G18: 60000 | H18: =E18*G18 -> 60000 | I18: Alta | J18: Ferretería náutica
A19: 15 | B19: Estructura Aerodinámica y Fuselaje | C19: Cat 3 - Rocketeers | D19: Guías de lanzamiento | E19: 1 | F19: Par | G19: 20000 | H19: =E19*G19 -> 20000 | I19: Alta | J19: Mecanizados | K19: Valor por definir
A20: 16 | B20: Herramientas de Taller y Consumibles | C20: Cat 3 - Rocketeers | D20: Herrajes y tornillos | E20: 1 | F20: Lote | G20: 50000 | H20: =E20*G20 -> 50000 | I20: Alta | J20: Ferretería | K20: Valor por definir
A21: 17 | B21: Logística de Lanzamiento, Transporte y Campo | C21: General - Toda Delegación | D21: Hospedaje en Finca - Santa Fe de Antioquia (Fin de semana) | E21: 1 | F21: Servicio | G21: 3000000 | H21: =E21*G21 -> 3000000 | I21: Alta | J21: Inmobiliaria / Airbnb | K21: Alojamiento para toda la delegación (docentes y equipos)
A22: 18 | B22: Logística de Lanzamiento, Transporte y Campo | C22: General - Toda Delegación | D22: Transporte terrestre ida y regreso (La Estrella - Santa Fe de Antioquia) | E22: 1 | F22: Servicio | G22: 900000 | H22: =E22*G22 -> 900000 | I22: Alta | J22: Empresa de transporte | K22: Bus / Busetas para todo el grupo
A23: 19 | B23: Herramientas de Taller y Consumibles | C23: General - Toda Delegación | D23: PLA (Impresión 3D) | E23: 1 | F23: Rollo | G23: 100000 | H23: =E23*G23 -> 100000 | I23: Alta | J23: Proveedor local
A24: 20 | B24: Herramientas de Taller y Consumibles | C24: General - Toda Delegación | D24: PETG + CF (Impresión 3D con fibra de carbono) | E24: 1 | F24: Rollo | G24: 120000 | H24: =E24*G24 -> 120000 | I24: Alta | J24: Proveedor local
A25: 21 | B25: Sistema de Recuperación y Seguridad | C25: General - Toda Delegación | D25: Tela Ripstop Paracaídas | E25: 1 | F25: Lote | G25: 100000 | H25: =E25*G25 -> 100000 | I25: Alta | J25: Textilera
A26: 22 | B26: Sistema de Recuperación y Seguridad | C26: General - Toda Delegación | D26: Nylon trenzado | E26: 1 | F26: Rollo | G26: 25000 | H26: =E26*G26 -> 25000 | I26: Media | J26: Ferretería
A27: 23 | B27: Herramientas de Taller y Consumibles | C27: General - Toda Delegación | D27: Pinturas | E27: 1 | F27: Lote | G27: 160000 | H27: =E27*G27 -> 160000 | I27: Alta | J27: Ferretería
A28: 24 | B28: Herramientas de Taller y Consumibles | C28: General - Toda Delegación | D28: Vinilo adhesivo | E28: 1 | F28: Lote | G28: 80000 | H28: =E28*G28 -> 80000 | I28: Media | J28: Papelería
A29: 25 | B29: Herramientas de Taller y Consumibles | C29: General - Toda Delegación | D29: Adhesivos para letras y parches de misión (Impreso) | E29: 1 | F29: Lote | G29: 70000 | H29: =E29*G29 -> 70000 | I29: Alta | J29: Litografía
A30: 26 | B30: Estructura Aerodinámica y Fuselaje | C30: General - Toda Delegación | D30: Resina Epóxica | E30: 5 | F30: Unidad | G30: 35000 | H30: =E30*G30 -> 175000 | I30: Alta | J30: Proveedor local
A31: 27 | B31: Herramientas de Taller y Consumibles | C31: General - Toda Delegación | D31: Boquilla acero endurecido | E31: 2 | F31: Unidad | G31: 40000 | H31: =E31*G31 -> 80000 | I31: Alta | J31: Proveedor local
A32: TOTAL GENERAL PRESUPUESTADO CCCD 2026 | H32: =SUM(H5:H31) -> 7990000

Sheet RELACION_GASTOS
A1: RELACIÓN Y CONTROL DE GASTOS REALES EJECUTADOS — CCCD 2026
A4: FECHA | B4: N° FACTURA | C4: PROVEEDOR | D4: ASIGNACIÓN (CAT) | E4: RUBRO FINANCIERO | F4: DESCRIPCIÓN | G4: CANTIDAD | H4: VALOR TOTAL (COP) | I4: FORMA DE PAGO | J4: RESPONSABLE | K4: OBSERVACIONES
A30: TOTAL GASTOS EJECUTADOS ACUMULADOS | H30: =SUM(H5:H29) -> 0
